any_to_md_cli/__init__.py
any_to_md_cli/cli.py
any_to_md_cli/converter.py
any_to_md_cli-0.1.1.dist-info/METADATA
any_to_md_cli-0.1.1.dist-info/WHEEL
any_to_md_cli-0.1.1.dist-info/entry_points.txt
any_to_md_cli-0.1.1.dist-info/top_level.txt
any_to_md_cli-0.1.1.dist-info/RECORD
