Metadata-Version: 2.4
Name: any-to-md-cli
Version: 0.1.1
Summary: A CLI tool to convert various file formats to Markdown using AI
Author-email: anywaifu <anywaifu@protonmail.com>
Classifier: Programming Language :: Python :: 3
Classifier: License :: OSI Approved :: MIT License
Classifier: Operating System :: OS Independent
Classifier: Topic :: Utilities
Classifier: Environment :: Console
Requires-Python: >=3.8
Requires-Dist: click>=8.0
Requires-Dist: litellm>=1.69
Provides-Extra: dev
Requires-Dist: pytest>=7.0; extra == "dev"
Requires-Dist: pytest-mock>=3.0; extra == "dev"
